{
  "last_updated": "2026-01-22T03:33:10.516328Z",
  "today": {
    "date": "2026-01-22",
    "total_gmv": 2109572.04,
    "total_gmv_usd": 37659.5,
    "orders": 2022,
    "unique_buyers": 1992,
    "unique_vendors": 1992,
    "aov": 1043.31,
    "aov_usd": 18.62,
    "frequency": 1.02,
    "gmv_per_poc": 1059.02,
    "gmv_per_poc_usd": 18.91
  },
  "same_day_last_week": {
    "date": "2026-01-15",
    "total_gmv": 1059069.65,
    "total_gmv_usd": 18906.22,
    "orders": 835,
    "unique_buyers": 822,
    "unique_vendors": 822,
    "aov": 1268.35,
    "aov_usd": 22.64,
    "frequency": 1.02,
    "gmv_per_poc": 1288.41,
    "gmv_per_poc_usd": 23.0
  },
  "mtd": {
    "start_date": "2026-01-01",
    "end_date": "2026-01-22",
    "total_gmv": 86204570.97,
    "total_gmv_usd": 1538900.17,
    "orders": 80123,
    "unique_buyers": 65473,
    "unique_vendors": 65473,
    "aov": 1075.9,
    "aov_usd": 19.21,
    "frequency": 1.22,
    "gmv_per_poc": 1316.64,
    "gmv_per_poc_usd": 23.5
  },
  "daily_history": [
    {
      "total_gmv": 228246.52,
      "total_gmv_usd": 4074.59,
      "orders": 96,
      "unique_buyers": 94,
      "unique_vendors": 94,
      "aov": 2377.57,
      "aov_usd": 42.44,
      "frequency": 1.02,
      "gmv_per_poc": 2428.15,
      "gmv_per_poc_usd": 43.35,
      "date": "2026-01-06"
    },
    {
      "total_gmv": 7083038.3,
      "total_gmv_usd": 126444.44,
      "orders": 5843,
      "unique_buyers": 5694,
      "unique_vendors": 5694,
      "aov": 1212.23,
      "aov_usd": 21.64,
      "frequency": 1.03,
      "gmv_per_poc": 1243.95,
      "gmv_per_poc_usd": 22.21,
      "date": "2026-01-07"
    },
    {
      "total_gmv": 6117701.07,
      "total_gmv_usd": 109211.51,
      "orders": 5704,
      "unique_buyers": 5570,
      "unique_vendors": 5570,
      "aov": 1072.53,
      "aov_usd": 19.15,
      "frequency": 1.02,
      "gmv_per_poc": 1098.33,
      "gmv_per_poc_usd": 19.61,
      "date": "2026-01-08"
    },
    {
      "total_gmv": 5511734.03,
      "total_gmv_usd": 98393.95,
      "orders": 5173,
      "unique_buyers": 5084,
      "unique_vendors": 5084,
      "aov": 1065.48,
      "aov_usd": 19.02,
      "frequency": 1.02,
      "gmv_per_poc": 1084.13,
      "gmv_per_poc_usd": 19.35,
      "date": "2026-01-09"
    },
    {
      "total_gmv": 4243436.84,
      "total_gmv_usd": 75752.66,
      "orders": 4271,
      "unique_buyers": 4198,
      "unique_vendors": 4198,
      "aov": 993.55,
      "aov_usd": 17.74,
      "frequency": 1.02,
      "gmv_per_poc": 1010.82,
      "gmv_per_poc_usd": 18.04,
      "date": "2026-01-10"
    },
    {
      "total_gmv": 1835750.21,
      "total_gmv_usd": 32771.31,
      "orders": 628,
      "unique_buyers": 607,
      "unique_vendors": 607,
      "aov": 2923.17,
      "aov_usd": 52.18,
      "frequency": 1.03,
      "gmv_per_poc": 3024.3,
      "gmv_per_poc_usd": 53.99,
      "date": "2026-01-11"
    },
    {
      "total_gmv": 7383935.41,
      "total_gmv_usd": 131815.97,
      "orders": 6308,
      "unique_buyers": 6160,
      "unique_vendors": 6160,
      "aov": 1170.57,
      "aov_usd": 20.9,
      "frequency": 1.02,
      "gmv_per_poc": 1198.69,
      "gmv_per_poc_usd": 21.4,
      "date": "2026-01-12"
    },
    {
      "total_gmv": 7055225.05,
      "total_gmv_usd": 125947.93,
      "orders": 6490,
      "unique_buyers": 6289,
      "unique_vendors": 6289,
      "aov": 1087.09,
      "aov_usd": 19.41,
      "frequency": 1.03,
      "gmv_per_poc": 1121.84,
      "gmv_per_poc_usd": 20.03,
      "date": "2026-01-13"
    },
    {
      "total_gmv": 6190268.09,
      "total_gmv_usd": 110506.95,
      "orders": 6207,
      "unique_buyers": 6059,
      "unique_vendors": 6059,
      "aov": 997.3,
      "aov_usd": 17.8,
      "frequency": 1.02,
      "gmv_per_poc": 1021.66,
      "gmv_per_poc_usd": 18.24,
      "date": "2026-01-14"
    },
    {
      "total_gmv": 5912587.95,
      "total_gmv_usd": 105549.89,
      "orders": 6178,
      "unique_buyers": 6004,
      "unique_vendors": 6004,
      "aov": 957.04,
      "aov_usd": 17.08,
      "frequency": 1.03,
      "gmv_per_poc": 984.77,
      "gmv_per_poc_usd": 17.58,
      "date": "2026-01-15"
    },
    {
      "total_gmv": 5556765.22,
      "total_gmv_usd": 99197.84,
      "orders": 5643,
      "unique_buyers": 5494,
      "unique_vendors": 5494,
      "aov": 984.72,
      "aov_usd": 17.58,
      "frequency": 1.03,
      "gmv_per_poc": 1011.42,
      "gmv_per_poc_usd": 18.06,
      "date": "2026-01-16"
    },
    {
      "total_gmv": 4311819.21,
      "total_gmv_usd": 76973.4,
      "orders": 4701,
      "unique_buyers": 4585,
      "unique_vendors": 4585,
      "aov": 917.21,
      "aov_usd": 16.37,
      "frequency": 1.03,
      "gmv_per_poc": 940.42,
      "gmv_per_poc_usd": 16.79,
      "date": "2026-01-17"
    },
    {
      "total_gmv": 1696248.3,
      "total_gmv_usd": 30280.96,
      "orders": 758,
      "unique_buyers": 730,
      "unique_vendors": 730,
      "aov": 2237.79,
      "aov_usd": 39.95,
      "frequency": 1.04,
      "gmv_per_poc": 2323.63,
      "gmv_per_poc_usd": 41.48,
      "date": "2026-01-18"
    },
    {
      "total_gmv": 7433245.08,
      "total_gmv_usd": 132696.24,
      "orders": 6428,
      "unique_buyers": 6254,
      "unique_vendors": 6254,
      "aov": 1156.39,
      "aov_usd": 20.64,
      "frequency": 1.03,
      "gmv_per_poc": 1188.56,
      "gmv_per_poc_usd": 21.22,
      "date": "2026-01-19"
    },
    {
      "total_gmv": 7274497.13,
      "total_gmv_usd": 129862.31,
      "orders": 6920,
      "unique_buyers": 6730,
      "unique_vendors": 6730,
      "aov": 1051.23,
      "aov_usd": 18.77,
      "frequency": 1.03,
      "gmv_per_poc": 1080.91,
      "gmv_per_poc_usd": 19.3,
      "date": "2026-01-20"
    },
    {
      "total_gmv": 6260500.52,
      "total_gmv_usd": 111760.72,
      "orders": 6753,
      "unique_buyers": 6610,
      "unique_vendors": 6610,
      "aov": 927.07,
      "aov_usd": 16.55,
      "frequency": 1.02,
      "gmv_per_poc": 947.13,
      "gmv_per_poc_usd": 16.91,
      "date": "2026-01-21"
    },
    {
      "total_gmv": 2109572.04,
      "total_gmv_usd": 37659.5,
      "orders": 2022,
      "unique_buyers": 1992,
      "unique_vendors": 1992,
      "aov": 1043.31,
      "aov_usd": 18.62,
      "frequency": 1.02,
      "gmv_per_poc": 1059.02,
      "gmv_per_poc_usd": 18.91,
      "date": "2026-01-22"
    }
  ],
  "moving_averages": {
    "ma_7d": {
      "gmv": 88347.28,
      "orders": 4746.43,
      "aov": 21.21,
      "unique_buyers": 4627.86,
      "frequency": 1.03,
      "gmv_per_poc": 21.81
    },
    "ma_15d": {
      "gmv": 93892.08,
      "orders": 4945.6,
      "aov": 22.12,
      "unique_buyers": 4824.4,
      "frequency": 1.03,
      "gmv_per_poc": 22.73
    }
  },
  "channel_breakdown_today": {
    "customer": {
      "gmv_usd": 18985.14,
      "orders": 700,
      "gmv_percent": 50.4,
      "orders_percent": 34.6
    },
    "cx_tlp": {
      "gmv_usd": 18674.36,
      "orders": 1322,
      "gmv_percent": 49.6,
      "orders_percent": 65.4
    }
  },
  "channel_breakdown_mtd": {
    "customer": {
      "gmv_usd": 1042344.18,
      "orders": 39098,
      "gmv_percent": 67.7,
      "orders_percent": 48.8
    },
    "cx_tlp": {
      "gmv_usd": 496556.0,
      "orders": 41025,
      "gmv_percent": 32.3,
      "orders_percent": 51.2
    }
  }
}